drl_lib/__init__.py
drl_lib/agents/__init__.py
drl_lib/agents/SAC/Q_network.py
drl_lib/agents/SAC/__init__.py
drl_lib/agents/SAC/agent_sac.py
drl_lib/agents/SAC/network.py
drl_lib/agents/SAC/policy_nn.py
drl_lib/agents/SAC/value_network.py
drl_lib/debugging/__init__.py
drl_lib/debugging/journaling.py
drl_lib/utils/__init__.py
drl_lib/utils/replay_buffer.py
drl_lib-0.0.0.dist-info/licenses/LICENSE
drl_lib-0.0.0.dist-info/METADATA
drl_lib-0.0.0.dist-info/WHEEL
drl_lib-0.0.0.dist-info/top_level.txt
drl_lib-0.0.0.dist-info/RECORD
