Metadata-Version: 2.4
Name: DRL-lib
Version: 0.0.0
Summary: A Deep Reinforcement Learning library implementing SAC and other algorithms
Author: Your Name
Author-email: Your Name <zendehdel.d@gmail.com>
Project-URL: Homepage, https://github.com/yourusername/drl-lib
Project-URL: Bug Tracker, https://github.com/yourusername/drl-lib/issues
Classifier: Programming Language :: Python :: 3
Classifier: License :: OSI Approved :: MIT License
Classifier: Operating System :: OS Independent
Requires-Python: >=3.7
License-File: LICENSE
Requires-Dist: torch>=1.7.0
Requires-Dist: gymnasium>=0.26.0
Requires-Dist: numpy>=1.19.0
Dynamic: author
Dynamic: license-file
Dynamic: requires-python
